odoo/addons/stock_release_channel/README.rst
odoo/addons/stock_release_channel/__init__.py
odoo/addons/stock_release_channel/__manifest__.py
odoo/addons/stock_release_channel/data/ir_cron_data.xml
odoo/addons/stock_release_channel/data/queue_job_data.xml
odoo/addons/stock_release_channel/demo/stock_release_channel.xml
odoo/addons/stock_release_channel/i18n/es.po
odoo/addons/stock_release_channel/i18n/fr.po
odoo/addons/stock_release_channel/i18n/it.po
odoo/addons/stock_release_channel/i18n/stock_release_channel.pot
odoo/addons/stock_release_channel/migrations/18.0.1.4.0/post-migration.py
odoo/addons/stock_release_channel/migrations/18.0.1.4.0/pre-migration.py
odoo/addons/stock_release_channel/models/__init__.py
odoo/addons/stock_release_channel/models/res_company.py
odoo/addons/stock_release_channel/models/res_config_settings.py
odoo/addons/stock_release_channel/models/res_partner.py
odoo/addons/stock_release_channel/models/stock_move.py
odoo/addons/stock_release_channel/models/stock_picking.py
odoo/addons/stock_release_channel/models/stock_release_channel.py
odoo/addons/stock_release_channel/readme/CONFIGURE.md
odoo/addons/stock_release_channel/readme/CONTRIBUTORS.md
odoo/addons/stock_release_channel/readme/CREDITS.md
odoo/addons/stock_release_channel/readme/DESCRIPTION.md
odoo/addons/stock_release_channel/readme/USAGE.md
odoo/addons/stock_release_channel/security/stock_release_channel.xml
odoo/addons/stock_release_channel/static/description/icon.png
odoo/addons/stock_release_channel/static/description/index.html
odoo/addons/stock_release_channel/static/src/js/progressbar_fractional_widget.esm.js
odoo/addons/stock_release_channel/static/src/scss/stock_release_channel.scss
odoo/addons/stock_release_channel/tests/__init__.py
odoo/addons/stock_release_channel/tests/common.py
odoo/addons/stock_release_channel/tests/test_assign_job.py
odoo/addons/stock_release_channel/tests/test_channel_action.py
odoo/addons/stock_release_channel/tests/test_channel_computed_fields.py
odoo_addon_stock_release_channel-18.0.1.5.2.1.dist-info/METADATA
odoo_addon_stock_release_channel-18.0.1.5.2.1.dist-info/WHEEL
odoo_addon_stock_release_channel-18.0.1.5.2.1.dist-info/top_level.txt
odoo_addon_stock_release_channel-18.0.1.5.2.1.dist-info/RECORD
