Metadata-Version: 2.1
Name: odoo-addon-stock_release_channel
Version: 18.0.1.5.2.1
Requires-Python: >=3.10
Requires-Dist: odoo-addon-queue_job==18.0.*
Requires-Dist: odoo-addon-stock_available_to_promise_release==18.0.*
Requires-Dist: odoo==18.0.*
Summary: Manage workload in WMS with release channels
Home-page: https://github.com/OCA/stock-logistics-release-channel
License: AGPL-3
Author: Camptocamp, BCIM, ACSONE SA/NV, Odoo Community Association (OCA)
Author-email: support@odoo-community.org
Classifier: Programming Language :: Python
Classifier: Framework :: Odoo
Classifier: Framework :: Odoo :: 18.0
Classifier: License :: OSI Approved :: GNU Affero General Public License v3
Classifier: Development Status :: 4 - Beta
